mkdocs_anti_ai_scraper_plugin/__init__.py
mkdocs_anti_ai_scraper_plugin-0.1.0.dist-info/METADATA
mkdocs_anti_ai_scraper_plugin-0.1.0.dist-info/WHEEL
mkdocs_anti_ai_scraper_plugin-0.1.0.dist-info/entry_points.txt
mkdocs_anti_ai_scraper_plugin-0.1.0.dist-info/RECORD
