Metadata-Version: 2.3
Name: mkdocs-anti-ai-scraper-plugin
Version: 0.1.0
Summary: Make it slightly harder for bots to steal your content
License: MIT
Author: six-two
Author-email: git@six-two.dev
Requires-Python: >=3.9
Classifier: License :: OSI Approved :: MIT License
Classifier: Programming Language :: Python :: 3
Classifier: Programming Language :: Python :: 3.9
Classifier: Programming Language :: Python :: 3.10
Classifier: Programming Language :: Python :: 3.11
Classifier: Programming Language :: Python :: 3.12
Classifier: Programming Language :: Python :: 3.13
Requires-Dist: mkdocs (>=1.5.0)
Requires-Dist: self-unzip-html (>=0.2.1,<0.3.0)
